package_folder/Aqouthe_.py
package_folder/Aqouthe_module.py
package_folder/__init__.py
Ather-1.3.dist-info/LICENCE
Ather-1.3.dist-info/METADATA
Ather-1.3.dist-info/WHEEL
Ather-1.3.dist-info/top_level.txt
Ather-1.3.dist-info/RECORD
