Metadata-Version: 2.1
Name: Ather
Version: 1.3
Summary: 걍 마음대로 쓰는 모듈
Home-page: UNKNOWN
Author: Aqouthe
Author-email: hoonie0929@gmail.com
License: MIT
Platform: UNKNOWN
Requires-Python: >=3
License-File: LICENCE
Requires-Dist: math
